{
  "app": "ONLINE Service Manager",
  "channel": "stable",
  "latest_version": "0.2.50",
  "tag": "v0.2.50",
  "release_title": "ONLINE Service Manager v0.2.50 Beta",
  "published_at": "2026-07-15T01:13:40",
  "download_url": "update/latest/ONLINE-Service-Manager-v0.2.50.zip",
  "file_name": "ONLINE-Service-Manager-v0.2.50.zip",
  "stable_download_url": "update/latest/ONLINE-Service-Manager.zip",
  "sha256": "0094440e6af5a95e6ad9c7edf223e194760732ce3f38b91785cf61fca1d4f5a4",
  "size_bytes": 56149392,
  "release_notes": [
    "Перший публічний Beta-реліз",
    "Developer Suite v1.1",
    "Website Publisher",
    "Public Release Gate"
  ],
  "min_supported_version": "0.2.0",
  "force_update": false
}
